jodcn/__init__.py
jodcn-0.3.dist-info/Licence.txt
jodcn-0.3.dist-info/METADATA
jodcn-0.3.dist-info/WHEEL
jodcn-0.3.dist-info/top_level.txt
jodcn-0.3.dist-info/RECORD
