Metadata-Version: 2.1
Name: jodcn
Version: 0.3
Summary: Package for Computer Networks 
Author: JOD
License: UNKNOWN
Platform: UNKNOWN
License-File: Licence.txt
